nerfview/__init__.py
nerfview/_renderer.py
nerfview/render_panel.py
nerfview/version.py
nerfview/viewer.py
nerfview-0.1.3.dist-info/METADATA
nerfview-0.1.3.dist-info/WHEEL
nerfview-0.1.3.dist-info/top_level.txt
nerfview-0.1.3.dist-info/RECORD
