Metadata-Version: 2.1
Name: nerfview
Version: 0.1.3
Summary: Interactive NeRF rendering web viewer
License: MIT
Project-URL: GitHub, https://github.com/hangg7/nerfview
Classifier: Programming Language :: Python :: 3
Classifier: Programming Language :: Python :: 3.8
Classifier: Programming Language :: Python :: 3.9
Classifier: Programming Language :: Python :: 3.10
Classifier: Programming Language :: Python :: 3.11
Classifier: Programming Language :: Python :: 3.12
Classifier: License :: OSI Approved :: MIT License
Classifier: Operating System :: OS Independent
Requires-Dist: viser >=0.2.1
Provides-Extra: dev
Requires-Dist: black ; extra == 'dev'
Requires-Dist: isort ; extra == 'dev'
Requires-Dist: ipdb ; extra == 'dev'
